MANIFEST.in
README.txt
Readme.txt
setup.cfg
setup.py
dijkstra_alg/__init__.py
dijkstra_alg/__main__.py
dijkstra_alg/dijkstra.py
dijkstra_alg/is_valid_input.py
dijkstra_alg.egg-info/PKG-INFO
dijkstra_alg.egg-info/SOURCES.txt
dijkstra_alg.egg-info/dependency_links.txt
dijkstra_alg.egg-info/requires.txt
dijkstra_alg.egg-info/top_level.txt
dijkstra_alg/tests/__init__.py
dijkstra_alg/tests/inv_test_matrix.txt
dijkstra_alg/tests/test_dijkstra.py
dijkstra_alg/tests/test_matrix.txt