Metadata-Version: 2.1
Name: dijkstra-alg
Version: 1.0.3
Summary: Пакет для поиска кратчайшего пути посредством алгоритма Дейкстры
Home-page: UNKNOWN
Author: Sokolov Lev
Author-email: vaxxo9000@gmail.com
License: UNKNOWN
Platform: UNKNOWN
